runnelpy/__init__.py
runnelpy/__main__.py
runnelpy/app.py
runnelpy/cli.py
runnelpy/compression.py
runnelpy/concurrency.py
runnelpy/constants.py
runnelpy/context.py
runnelpy/discovery.py
runnelpy/events.py
runnelpy/exceptions.py
runnelpy/executor.py
runnelpy/hashing.py
runnelpy/interfaces.py
runnelpy/logging.py
runnelpy/lua/lock_extend.lua
runnelpy/lua/lock_release.lua
runnelpy/middleware/__init__.py
runnelpy/middleware/ack.py
runnelpy/middleware/dead.py
runnelpy/middleware/deserialize.py
runnelpy/middleware/take.py
runnelpy/processor.py
runnelpy/record.py
runnelpy/runner.py
runnelpy/serialization.py
runnelpy/settings.py
runnelpy/stream.py
runnelpy/types.py
runnelpy/utils.py
runnelpy/worker.py
runnelpy-0.3.1.dist-info/LICENSE
runnelpy-0.3.1.dist-info/METADATA
runnelpy-0.3.1.dist-info/WHEEL
runnelpy-0.3.1.dist-info/entry_points.txt
runnelpy-0.3.1.dist-info/RECORD
