Metadata-Version: 2.3
Name: runnelpy
Version: 0.3.1
Summary: Distributed event processing for Python based on Redis Streams
License: LGPL-3.0-only
Keywords: data,stream,processing,redis,async
Author: Matt Westcott
Author-email: m.westcott@gmail.com
Requires-Python: >=3.7,<4.0
Classifier: License :: OSI Approved :: GNU Lesser General Public License v3 (LGPLv3)
Classifier: Programming Language :: Python :: 3
Classifier: Programming Language :: Python :: 3.7
Classifier: Programming Language :: Python :: 3.8
Classifier: Programming Language :: Python :: 3.9
Classifier: Programming Language :: Python :: 3.10
Classifier: Programming Language :: Python :: 3.11
Classifier: Programming Language :: Python :: 3.12
Classifier: Programming Language :: Python :: 3.13
Provides-Extra: fast
Requires-Dist: aiostream (>=0.4.1,<0.5.0)
Requires-Dist: anyio (>=3.7.1,<4.0.0)
Requires-Dist: aredis (>=1.1.8,<2.0.0)
Requires-Dist: colorama (>=0.4.6,<0.5.0)
Requires-Dist: croniter (>=0.3.34,<0.4.0)
Requires-Dist: hiredis (>=2.3.2,<3.0.0)
Requires-Dist: lz4 (>=3.1.0,<4.0.0) ; extra == "fast"
Requires-Dist: orjson (>=3.2.1,<4.0.0) ; extra == "fast"
Requires-Dist: pydantic (>=1.5.1,<2.0.0)
Requires-Dist: pytz (>=2024.2,<2025.0)
Requires-Dist: structlog (>=20.1.0,<21.0.0)
Requires-Dist: typer (>=0.3.0,<0.4.0)
Requires-Dist: uvloop (>=0.14.0,<0.15.0) ; extra == "fast"
Requires-Dist: xxhash (>=1.4.4,<2.0.0) ; extra == "fast"
